mlflow_tritonserver/__init__.py
mlflow_tritonserver/__version__.py
mlflow_tritonserver/config.py
mlflow_tritonserver/deployments.py
mlflow_tritonserver/mlflow_tritonserver_cli.py
mlflow_tritonserver/triton_flavor.py
mlflow_tritonserver-1.1.0.dist-info/LICENSE
mlflow_tritonserver-1.1.0.dist-info/METADATA
mlflow_tritonserver-1.1.0.dist-info/WHEEL
mlflow_tritonserver-1.1.0.dist-info/entry_points.txt
mlflow_tritonserver-1.1.0.dist-info/top_level.txt
mlflow_tritonserver-1.1.0.dist-info/RECORD
