Metadata-Version: 2.1
Name: mlflow-tritonserver
Version: 1.1.0
Summary: Tritonserver Mlflow Deployment
License: Apache 2.0
Project-URL: Documentation, https://github.com/msclock/mlflow-tritonserver.git
Project-URL: Source, https://github.com/msclock/mlflow-tritonserver.git
Project-URL: Tracker, https://github.com/msclock/mlflow-tritonserver/issues
Keywords: machine-learning,deep-learning,inference,tritonserver,mlflow
Classifier: Development Status :: 4 - Beta
Classifier: License :: OSI Approved :: Apache Software License
Classifier: Operating System :: OS Independent
Classifier: Intended Audience :: Developers
Classifier: Intended Audience :: Science/Research
Classifier: Programming Language :: Python :: 3
Classifier: Programming Language :: Python :: 3.7
Classifier: Programming Language :: Python :: 3.8
Classifier: Programming Language :: Python :: 3.9
Classifier: Programming Language :: Python :: 3.10
Classifier: Topic :: Software Development :: Libraries
Classifier: Topic :: Software Development :: Libraries :: Python Modules
Classifier: Topic :: Education
Classifier: Topic :: Scientific/Engineering
Classifier: Topic :: Scientific/Engineering :: Artificial Intelligence
Requires-Python: >=3.7
License-File: LICENSE
Requires-Dist: mlflow (<3.0,>=2.2.1)
Requires-Dist: tritonclient[all] (==2.35.0)
Requires-Dist: boto3 (==1.28.2)
Provides-Extra: dev
Requires-Dist: black (>=22.8) ; extra == 'dev'
Requires-Dist: build (>=0.8) ; extra == 'dev'
Requires-Dist: ipython (>=7.16) ; extra == 'dev'
Requires-Dist: isort (>=5.10) ; extra == 'dev'
Requires-Dist: pdbpp (>=0.10) ; extra == 'dev'
Requires-Dist: pip (>=21.1) ; extra == 'dev'
Requires-Dist: psutil (~=5.1) ; extra == 'dev'
Requires-Dist: twine (>=4.0) ; extra == 'dev'
Provides-Extra: test
Requires-Dist: pytest (>=5.2) ; extra == 'test'
Requires-Dist: pytest-mock (>=3.8.2) ; extra == 'test'
